neem_pycram_interface/__init__.py
neem_pycram_interface/neem_pycram_interface.py
neem_pycram_interface/utils.py
neem_pycram_interface-1.0.176.dist-info/licenses/LICENSE
neem_pycram_interface-1.0.176.dist-info/METADATA
neem_pycram_interface-1.0.176.dist-info/WHEEL
neem_pycram_interface-1.0.176.dist-info/top_level.txt
neem_pycram_interface-1.0.176.dist-info/RECORD
