Metadata-Version: 2.4
Name: neem_pycram_interface
Version: 1.0.176
Summary: Using NEEMs database with the help of NEEMQuery python package to redo or replay neems using PyCRAM
Author-email: Abdelrhman Bassiouny <abassiou@uni-bremen.de>
License:                     GNU GENERAL PUBLIC LICENSE
Project-URL: Homepage, https://github.com/AbdelrhmanBassiouny/NEEMPyCRAMInterface
Keywords: query,neems,database,sql,robotics,knowledge,memories,episodic,replay,redo actions,pycram
Classifier: Programming Language :: Python :: 3
Requires-Python: >=3.8
License-File: LICENSE
Requires-Dist: NEEMQuery
Requires-Dist: bs4
Dynamic: license-file
